{
  "1": {
    "type": "",
    "grunt": "Blanche"
  },
  "2": {
    "type": "",
    "grunt": "Candela"
  },
  "3": {
    "type": "",
    "grunt": "Spark"
  },
  "4": {
    "type": "",
    "grunt": "Male"
  },
  "5": {
    "type": "",
    "grunt": "Female",
    "pokemon": {
      "1": {
        "ids": [
          143
        ],
        "isReward": true
      },
      "2": {
        "ids": [
          62,
          143,
          282
        ],
        "isReward": false
      },
      "3": {
        "ids": [
          143,
          149,
          130
        ],
        "isReward": false
      }
    }
  },
  "6": {
    "type": "Bug",
    "grunt": "Female"
  },
  "7": {
    "type": "Bug",
    "grunt": "Male",
    "pokemon": {
      "1": {
        "ids": [
          451,
          213,
          595
        ],
        "isReward": true
      },
      "2": {
        "ids": [
          13,
          14,
          15
        ],
        "isReward": true
      },
      "3": {
        "ids": [
          205,
          212,
          15
        ],
        "isReward": false
      }
    }
  },
  "10": {
    "type": "Dark",
    "grunt": "Female",
    "pokemon": {
      "1": {
        "ids": [
          19,
          509,
          198
        ],
        "isReward": true
      },
      "2": {
        "ids": [
          198,
          434,
          20
        ],
        "isReward": true
      },
      "3": {
        "ids": [
          20,
          430,
          332
        ],
        "isReward": false
      }
    }
  },
  "11": {
    "type": "Dark",
    "grunt": "Male"
  },
  "12": {
    "type": "Dragon",
    "grunt": "Female",
    "pokemon": {
      "1": {
        "ids": [
          147,
          103
        ],
        "isReward": true
      },
      "2": {
        "ids": [
          103,
          330
        ],
        "isReward": false
      },
      "3": {
        "ids": [
          149,
          148,
          330
        ],
        "isReward": false
      }
    }
  },
  "13": {
    "type": "Dragon",
    "grunt": "Male"
  },
  "14": {
    "type": "Fairy",
    "grunt": "Female",
    "pokemon": {
      "1": {
        "ids": [
          209,
          280
        ],
        "isReward": true
      },
      "2": {
        "ids": [
          281,
          209,
          210
        ],
        "isReward": true
      },
      "3": {
        "ids": [
          210,
          281
        ],
        "isReward": false
      }
    }
  },
  "15": {
    "type": "Fairy",
    "grunt": "Male"
  },
  "16": {
    "type": "Fighting",
    "grunt": "Female",
    "pokemon": {
      "1": {
        "ids": [
          296,
          107,
          106
        ],
        "isReward": true
      },
      "2": {
        "ids": [
          107,
          106
        ],
        "isReward": true
      },
      "3": {
        "ids": [
          68,
          107,
          106
        ],
        "isReward": false
      }
    }
  },
  "17": {
    "type": "Fighting",
    "grunt": "Male"
  },
  "18": {
    "type": "Fire",
    "grunt": "Female",
    "pokemon": {
      "1": {
        "ids": [
          322,
          155,
          37
        ],
        "isReward": true
      },
      "2": {
        "ids": [
          126,
          156
        ],
        "isReward": false
      },
      "3": {
        "ids": [
          38,
          157,
          323
        ],
        "isReward": false
      }
    }
  },
  "19": {
    "type": "Fire",
    "grunt": "Male"
  },
  "20": {
    "type": "Flying",
    "grunt": "Female",
    "pokemon": {
      "1": {
        "ids": [
          177,
          41,
          580
        ],
        "isReward": true
      },
      "2": {
        "ids": [
          397,
          42,
          178
        ],
        "isReward": false
      },
      "3": {
        "ids": [
          149,
          169,
          130
        ],
        "isReward": false
      }
    }
  },
  "21": {
    "type": "Flying",
    "grunt": "Male"
  },
  "22": {
    "type": "Grass",
    "grunt": "Female"
  },
  "23": {
    "type": "Grass",
    "grunt": "Male",
    "pokemon": {
      "1": {
        "ids": [
          43,
          152,
          331
        ],
        "isReward": true
      },
      "2": {
        "ids": [
          44,
          153
        ],
        "isReward": false
      },
      "3": {
        "ids": [
          591,
          332,
          154
        ],
        "isReward": false
      }
    }
  },
  "24": {
    "type": "Ground",
    "grunt": "Female"
  },
  "25": {
    "type": "Ground",
    "grunt": "Male",
    "pokemon": {
      "1": {
        "ids": [
          74,
          449,
          50
        ],
        "isReward": true
      },
      "2": {
        "ids": [
          449,
          50
        ],
        "isReward": false
      },
      "3": {
        "ids": [
          450,
          76,
          323
        ],
        "isReward": false
      }
    }
  },
  "26": {
    "type": "Ice",
    "grunt": "Female",
    "pokemon": {
      "1": {
        "ids": [
          37,
          27,
          220
        ],
        "isReward": true
      },
      "2": {
        "ids": [
          28,
          459,
          38
        ],
        "isReward": false
      },
      "3": {
        "ids": [
          91,
          460,
          131
        ],
        "isReward": false
      }
    }
  },
  "27": {
    "type": "Ice",
    "grunt": "Male"
  },
  "28": {
    "type": "",
    "grunt": "Female"
  },
  "29": {
    "type": "",
    "grunt": "Male"
  },
  "30": {
    "type": "Normal",
    "grunt": "Female"
  },
  "31": {
    "type": "Normal",
    "grunt": "Male",
    "pokemon": {
      "1": {
        "ids": [
          504,
          519,
          293
        ],
        "isReward": true
      },
      "2": {
        "ids": [
          20,
          19,
          294
        ],
        "isReward": true
      },
      "3": {
        "ids": [
          20,
          217,
          400
        ],
        "isReward": false
      }
    }
  },
  "32": {
    "type": "Poison",
    "grunt": "Female",
    "pokemon": {
      "1": {
        "ids": [
          590,
          41
        ],
        "isReward": true
      },
      "2": {
        "ids": [
          33,
          30
        ],
        "isReward": true
      },
      "3": {
        "ids": [
          110,
          89
        ],
        "isReward": false
      }
    }
  },
  "33": {
    "type": "Poison",
    "grunt": "Male"
  },
  "34": {
    "type": "Psychic",
    "grunt": "Female"
  },
  "35": {
    "type": "Psychic",
    "grunt": "Male",
    "pokemon": {
      "1": {
        "ids": [
          177,
          63,
          325
        ],
        "isReward": true
      },
      "2": {
        "ids": [
          203,
          280
        ],
        "isReward": true
      },
      "3": {
        "ids": [
          65,
          375,
          97
        ],
        "isReward": false
      }
    }
  },
  "36": {
    "type": "Rock",
    "grunt": "Female"
  },
  "37": {
    "type": "Rock",
    "grunt": "Male",
    "pokemon": {
      "1": {
        "ids": [
          95,
          345,
          347
        ],
        "isReward": true
      },
      "2": {
        "ids": [
          345,
          347,
          75
        ],
        "isReward": true
      },
      "3": {
        "ids": [
          95,
          208,
          76
        ],
        "isReward": false
      }
    }
  },
  "38": {
    "type": "Water",
    "grunt": "Female",
    "pokemon": {
      "1": {
        "ids": [
          54,
          320,
          158
        ],
        "isReward": true
      },
      "2": {
        "ids": [
          55,
          159
        ],
        "isReward": false
      },
      "3": {
        "ids": [
          160,
          55,
          321
        ],
        "isReward": false
      }
    }
  },
  "39": {
    "type": "Water",
    "grunt": "Male",
    "pokemon": {
      "1": {
        "ids": [
          129
        ],
        "isReward": true
      },
      "2": {
        "ids": [
          129
        ],
        "isReward": false
      },
      "3": {
        "ids": [
          129,
          130
        ],
        "isReward": false
      }
    }
  },
  "41": {
    "type": "",
    "grunt": "Leader Cliff",
    "pokemon": {
      "1": {
        "ids": [
          81
        ],
        "isReward": true
      },
      "2": {
        "ids": [
          127,
          3,
          139
        ],
        "isReward": false
      },
      "3": {
        "ids": [
          248,
          319,
          323
        ],
        "isReward": false
      }
    }
  },
  "42": {
    "type": "",
    "grunt": "Leader Arlo",
    "pokemon": {
      "1": {
        "ids": [
          29
        ],
        "isReward": true
      },
      "2": {
        "ids": [
          208,
          346,
          169
        ],
        "isReward": false
      },
      "3": {
        "ids": [
          212,
          6,
          348
        ],
        "isReward": false
      }
    }
  },
  "43": {
    "type": "",
    "grunt": "Leader Sierra",
    "pokemon": {
      "1": {
        "ids": [
          374
        ],
        "isReward": true
      },
      "2": {
        "ids": [
          319,
          330,
          131
        ],
        "isReward": false
      },
      "3": {
        "ids": [
          229,
          65,
          275
        ],
        "isReward": false
      }
    }
  },
  "44": {
    "type": "",
    "grunt": "Giovanni",
    "pokemon": {
      "1": {
        "ids": [
          53
        ],
        "isReward": false
      },
      "2": {
        "ids": [
          445,
          34,
          91
        ],
        "isReward": false
      },
      "3": {
        "ids": [
          379
        ],
        "isReward": true
      }
    }
  },
  "45": {
    "type": "",
    "grunt": "Decoy Grunt"
  },
  "46": {
    "type": "",
    "grunt": "Decoy Grunt",
    "pokemon": {
      "1": {
        "ids": [
          69
        ],
        "isReward": true
      },
      "2": {
        "ids": [
          70,
          20
        ],
        "isReward": true
      },
      "3": {
        "ids": [
          20,
          143
        ],
        "isReward": false
      }
    }
  },
  "47": {
    "type": "Ghost",
    "grunt": "Female"
  },
  "48": {
    "type": "Ghost",
    "grunt": "Male",
    "pokemon": {
      "1": {
        "ids": [
          355,
          622
        ],
        "isReward": true
      },
      "2": {
        "ids": [
          356,
          354
        ],
        "isReward": false
      },
      "3": {
        "ids": [
          354,
          477,
          623
        ],
        "isReward": false
      }
    }
  },
  "49": {
    "type": "Electric",
    "grunt": "Female",
    "pokemon": {
      "1": {
        "ids": [
          403,
          179,
          522
        ],
        "isReward": true
      },
      "2": {
        "ids": [
          125,
          100
        ],
        "isReward": true
      },
      "3": {
        "ids": [
          181,
          523,
          405
        ],
        "isReward": false
      }
    }
  },
  "50": {
    "type": "Electric",
    "grunt": "Male"
  },
  "53": {
    "type": "",
    "grunt": "Jessie"
  },
  "54": {
    "type": "",
    "grunt": "James"
  },
  "352": {
    "type": "",
    "grunt": "Kecleon"
  },
  "500": {
    "type": "",
    "grunt": "Robbenprinz"
  },
  "501": {
    "type": "",
    "grunt": "Alehouou"
  },
  "502": {
    "type": "",
    "grunt": "Leon9715"
  },
  "503": {
    "type": "",
    "grunt": "Brissete"
  },
  "504": {
    "type": "",
    "grunt": "Terureruru"
  },
  "505": {
    "type": "",
    "grunt": "Bathazarpokemom"
  },
  "506": {
    "type": "",
    "grunt": "AbsolFairy"
  },
  "507": {
    "type": "",
    "grunt": "MajinSage"
  },
  "508": {
    "type": "",
    "grunt": "Cave Trainer"
  },
  "509": {
    "type": "",
    "grunt": "Ocean Trainer"
  },
  "510": {
    "type": "",
    "grunt": "Savannah Trainer"
  }
}
