{"pokemon_name_1": "Bulbizarre",
  "pokemon_name_2": "Herbizarre",
  "pokemon_name_3": "Florizarre",
  "pokemon_name_4": "Salamèche",
  "pokemon_name_5": "Reptincel",
  "pokemon_name_6": "Dracaufeu",
  "pokemon_name_7": "Carapuce",
  "pokemon_name_8": "Carabaffe",
  "pokemon_name_9": "Tortank",
  "pokemon_name_10": "Chenipan",
  "pokemon_name_11": "Chrysacier",
  "pokemon_name_12": "Papilusion",
  "pokemon_name_13": "Aspicot",
  "pokemon_name_14": "Coconfort",
  "pokemon_name_15": "Dardargnan",
  "pokemon_name_16": "Roucool",
  "pokemon_name_17": "Roucoups",
  "pokemon_name_18": "Roucarnage",
  "pokemon_name_19": "Rattata",
  "pokemon_name_20": "Rattatac",
  "pokemon_name_21": "Piafabec",
  "pokemon_name_22": "Rapasdepic",
  "pokemon_name_23": "Abo",
  "pokemon_name_24": "Arbok",
  "pokemon_name_25": "Pikachu",
  "pokemon_name_26": "Raichu",
  "pokemon_name_27": "Sabelette",
  "pokemon_name_28": "Sablaireau",
  "pokemon_name_29": "Nidoran♀",
  "pokemon_name_30": "Nidorina",
  "pokemon_name_31": "Nidoqueen",
  "pokemon_name_32": "Nidoran♂",
  "pokemon_name_33": "Nidorino",
  "pokemon_name_34": "Nidoking",
  "pokemon_name_35": "Mélofée",
  "pokemon_name_36": "Mélodelfe",
  "pokemon_name_37": "Goupix",
  "pokemon_name_38": "Feunard",
  "pokemon_name_39": "Rondoudou",
  "pokemon_name_40": "Grodoudou",
  "pokemon_name_41": "Nosferapti",
  "pokemon_name_42": "Nosferalto",
  "pokemon_name_43": "Mystherbe",
  "pokemon_name_44": "Ortide",
  "pokemon_name_45": "Rafflesia",
  "pokemon_name_46": "Paras",
  "pokemon_name_47": "Parasect",
  "pokemon_name_48": "Mimitoss",
  "pokemon_name_49": "Aéromite",
  "pokemon_name_50": "Taupiqueur",
  "pokemon_name_51": "Triopikeur",
  "pokemon_name_52": "Miaouss",
  "pokemon_name_53": "Persian",
  "pokemon_name_54": "Psykokwak",
  "pokemon_name_55": "Akwakwak",
  "pokemon_name_56": "Férosinge",
  "pokemon_name_57": "Colossinge",
  "pokemon_name_58": "Caninos",
  "pokemon_name_59": "Arcanin",
  "pokemon_name_60": "Ptitard",
  "pokemon_name_61": "Têtarte",
  "pokemon_name_62": "Tartard",
  "pokemon_name_63": "Abra",
  "pokemon_name_64": "Kadabra",
  "pokemon_name_65": "Alakazam",
  "pokemon_name_66": "Machoc",
  "pokemon_name_67": "Machopeur",
  "pokemon_name_68": "Mackogneur",
  "pokemon_name_69": "Chétiflor",
  "pokemon_name_70": "Boustiflor",
  "pokemon_name_71": "Empiflor",
  "pokemon_name_72": "Tentacool",
  "pokemon_name_73": "Tentacruel",
  "pokemon_name_74": "Racaillou",
  "pokemon_name_75": "Gravalanch",
  "pokemon_name_76": "Grolem",
  "pokemon_name_77": "Ponyta",
  "pokemon_name_78": "Galopa",
  "pokemon_name_79": "Ramoloss",
  "pokemon_name_80": "Flagadoss",
  "pokemon_name_81": "Magnéti",
  "pokemon_name_82": "Magnéton",
  "pokemon_name_83": "Canarticho",
  "pokemon_name_84": "Doduo",
  "pokemon_name_85": "Dodrio",
  "pokemon_name_86": "Otaria",
  "pokemon_name_87": "Lamantine",
  "pokemon_name_88": "Tadmorv",
  "pokemon_name_89": "Grotadmorv",
  "pokemon_name_90": "Kokiyas",
  "pokemon_name_91": "Crustabri",
  "pokemon_name_92": "Fantominus",
  "pokemon_name_93": "Spectrum",
  "pokemon_name_94": "Ectoplasma",
  "pokemon_name_95": "Onix",
  "pokemon_name_96": "Soporifik",
  "pokemon_name_97": "Hypnomade",
  "pokemon_name_98": "Krabby",
  "pokemon_name_99": "Krabboss",
  "pokemon_name_100": "Voltorbe",
  "pokemon_name_101": "Électrode",
  "pokemon_name_102": "Noeunoeuf",
  "pokemon_name_103": "Noadkoko",
  "pokemon_name_104": "Osselait",
  "pokemon_name_105": "Ossatueur",
  "pokemon_name_106": "Kicklee",
  "pokemon_name_107": "Tygnon",
  "pokemon_name_108": "Excelangue",
  "pokemon_name_109": "Smogo",
  "pokemon_name_110": "Smogogo",
  "pokemon_name_111": "Rhinocorne",
  "pokemon_name_112": "Rhinoféros",
  "pokemon_name_113": "Leveinard",
  "pokemon_name_114": "Saquedeneu",
  "pokemon_name_115": "Kangourex",
  "pokemon_name_116": "Hypotrempe",
  "pokemon_name_117": "Hypocéan",
  "pokemon_name_118": "Poissirène",
  "pokemon_name_119": "Poissoroy",
  "pokemon_name_120": "Stari",
  "pokemon_name_121": "Staross",
  "pokemon_name_122": "M. Mime",
  "pokemon_name_123": "Insécateur",
  "pokemon_name_124": "Lippoutou",
  "pokemon_name_125": "Élektek",
  "pokemon_name_126": "Magmar",
  "pokemon_name_127": "Scarabrute",
  "pokemon_name_128": "Tauros",
  "pokemon_name_129": "Magicarpe",
  "pokemon_name_130": "Léviator",
  "pokemon_name_131": "Lokhlass",
  "pokemon_name_132": "Métamorph",
  "pokemon_name_133": "Évoli",
  "pokemon_name_134": "Aquali",
  "pokemon_name_135": "Voltali",
  "pokemon_name_136": "Pyroli",
  "pokemon_name_137": "Porygon",
  "pokemon_name_138": "Amonita",
  "pokemon_name_139": "Amonistar",
  "pokemon_name_140": "Kabuto",
  "pokemon_name_141": "Kabutops",
  "pokemon_name_142": "Ptéra",
  "pokemon_name_143": "Ronflex",
  "pokemon_name_144": "Artikodin",
  "pokemon_name_145": "Électhor",
  "pokemon_name_146": "Sulfura",
  "pokemon_name_147": "Minidraco",
  "pokemon_name_148": "Draco",
  "pokemon_name_149": "Dracolosse",
  "pokemon_name_150": "Mewtwo",
  "pokemon_name_151": "Mew",
  "pokemon_name_152": "Germignon",
  "pokemon_name_153": "Macronium",
  "pokemon_name_154": "Méganium",
  "pokemon_name_155": "Héricendre",
  "pokemon_name_156": "Feurisson",
  "pokemon_name_157": "Typhlosion",
  "pokemon_name_158": "Kaiminus",
  "pokemon_name_159": "Crocrodil",
  "pokemon_name_160": "Aligatueur",
  "pokemon_name_161": "Fouinette",
  "pokemon_name_162": "Fouinar",
  "pokemon_name_163": "Hoothoot",
  "pokemon_name_164": "Noarfang",
  "pokemon_name_165": "Coxy",
  "pokemon_name_166": "Coxyclaque",
  "pokemon_name_167": "Mimigal",
  "pokemon_name_168": "Migalos",
  "pokemon_name_169": "Nostenfer",
  "pokemon_name_170": "Loupio",
  "pokemon_name_171": "Lanturn",
  "pokemon_name_172": "Pichu",
  "pokemon_name_173": "Mélo",
  "pokemon_name_174": "Toudoudou",
  "pokemon_name_175": "Togepi",
  "pokemon_name_176": "Togetic",
  "pokemon_name_177": "Natu",
  "pokemon_name_178": "Xatu",
  "pokemon_name_179": "Wattouat",
  "pokemon_name_180": "Lainergie",
  "pokemon_name_181": "Pharamp",
  "pokemon_name_182": "Joliflor",
  "pokemon_name_183": "Marill",
  "pokemon_name_184": "Azumarill",
  "pokemon_name_185": "Simularbre",
  "pokemon_name_186": "Tarpaud",
  "pokemon_name_187": "Granivol",
  "pokemon_name_188": "Floravol",
  "pokemon_name_189": "Cotovol",
  "pokemon_name_190": "Capumain",
  "pokemon_name_191": "Tournegrin",
  "pokemon_name_192": "Héliatronc",
  "pokemon_name_193": "Yanma",
  "pokemon_name_194": "Axoloto",
  "pokemon_name_195": "Maraiste",
  "pokemon_name_196": "Mentali",
  "pokemon_name_197": "Noctali",
  "pokemon_name_198": "Cornèbre",
  "pokemon_name_199": "Roigada",
  "pokemon_name_200": "Feuforêve",
  "pokemon_name_201": "Zarbi",
  "pokemon_name_202": "Qulbutoké",
  "pokemon_name_203": "Girafarig",
  "pokemon_name_204": "Pomdepik",
  "pokemon_name_205": "Foretress",
  "pokemon_name_206": "Insolourdo",
  "pokemon_name_207": "Scorplane",
  "pokemon_name_208": "Steelix",
  "pokemon_name_209": "Snubbull",
  "pokemon_name_210": "Granbull",
  "pokemon_name_211": "Qwilfish",
  "pokemon_name_212": "Cizayox",
  "pokemon_name_213": "Caratroc",
  "pokemon_name_214": "Scarhino",
  "pokemon_name_215": "Farfuret",
  "pokemon_name_216": "Teddiursa",
  "pokemon_name_217": "Ursaring",
  "pokemon_name_218": "Limagma",
  "pokemon_name_219": "Volcaropod",
  "pokemon_name_220": "Marcacrin",
  "pokemon_name_221": "Cochignon",
  "pokemon_name_222": "Corayon",
  "pokemon_name_223": "Rémoraid",
  "pokemon_name_224": "Octillery",
  "pokemon_name_225": "Cadoizo",
  "pokemon_name_226": "Démanta",
  "pokemon_name_227": "Airmure",
  "pokemon_name_228": "Malosse",
  "pokemon_name_229": "Démolosse",
  "pokemon_name_230": "Hyporoi",
  "pokemon_name_231": "Phanpy",
  "pokemon_name_232": "Donphan",
  "pokemon_name_233": "Porygon2",
  "pokemon_name_234": "Cerfrousse",
  "pokemon_name_235": "Queulorior",
  "pokemon_name_236": "Debugant",
  "pokemon_name_237": "Kapoera",
  "pokemon_name_238": "Lippouti",
  "pokemon_name_239": "Élekid",
  "pokemon_name_240": "Magby",
  "pokemon_name_241": "Écrémeuh",
  "pokemon_name_242": "Leuphorie",
  "pokemon_name_243": "Raikou",
  "pokemon_name_244": "Entei",
  "pokemon_name_245": "Suicune",
  "pokemon_name_246": "Embrylex",
  "pokemon_name_247": "Ymphect",
  "pokemon_name_248": "Tyranocif",
  "pokemon_name_249": "Lugia",
  "pokemon_name_250": "Ho-Oh",
  "pokemon_name_251": "Celebi",
  "pokemon_name_252": "Arcko",
  "pokemon_name_253": "Massko",
  "pokemon_name_254": "Jungko",
  "pokemon_name_255": "Poussifeu",
  "pokemon_name_256": "Galifeu",
  "pokemon_name_257": "Braségali",
  "pokemon_name_258": "Gobou",
  "pokemon_name_259": "Flobio",
  "pokemon_name_260": "Laggron",
  "pokemon_name_261": "Medhyèna",
  "pokemon_name_262": "Grahyèna",
  "pokemon_name_263": "Zigzaton",
  "pokemon_name_264": "Linéon",
  "pokemon_name_265": "Chenipotte",
  "pokemon_name_266": "Armulys",
  "pokemon_name_267": "Charmillon",
  "pokemon_name_268": "Blindalys",
  "pokemon_name_269": "Papinox",
  "pokemon_name_270": "Nénupiot",
  "pokemon_name_271": "Lombre",
  "pokemon_name_272": "Ludicolo",
  "pokemon_name_273": "Grainipiot",
  "pokemon_name_274": "Pifeuil",
  "pokemon_name_275": "Tengalice",
  "pokemon_name_276": "Nirondelle",
  "pokemon_name_277": "Hélédelle",
  "pokemon_name_278": "Goélise",
  "pokemon_name_279": "Bekipan",
  "pokemon_name_280": "Tarsal",
  "pokemon_name_281": "Kirlia",
  "pokemon_name_282": "Gardevoir",
  "pokemon_name_283": "Arakdo",
  "pokemon_name_284": "Maskadra",
  "pokemon_name_285": "Balignon",
  "pokemon_name_286": "Chapignon",
  "pokemon_name_287": "Parecool",
  "pokemon_name_288": "Vigoroth",
  "pokemon_name_289": "Monaflèmit",
  "pokemon_name_290": "Ningale",
  "pokemon_name_291": "Ninjask",
  "pokemon_name_292": "Munja",
  "pokemon_name_293": "Chuchmur",
  "pokemon_name_294": "Ramboum",
  "pokemon_name_295": "Brouhabam",
  "pokemon_name_296": "Makuhita",
  "pokemon_name_297": "Hariyama",
  "pokemon_name_298": "Azurill",
  "pokemon_name_299": "Tarinor",
  "pokemon_name_300": "Skitty",
  "pokemon_name_301": "Delcatty",
  "pokemon_name_302": "Ténéfix",
  "pokemon_name_303": "Mysdibule",
  "pokemon_name_304": "Galekid",
  "pokemon_name_305": "Galegon",
  "pokemon_name_306": "Galeking",
  "pokemon_name_307": "Méditikka",
  "pokemon_name_308": "Charmina",
  "pokemon_name_309": "Dynavolt",
  "pokemon_name_310": "Élecsprint",
  "pokemon_name_311": "Posipi",
  "pokemon_name_312": "Négapi",
  "pokemon_name_313": "Muciole",
  "pokemon_name_314": "Lumivole",
  "pokemon_name_315": "Rosélia",
  "pokemon_name_316": "Gloupti",
  "pokemon_name_317": "Avaltout",
  "pokemon_name_318": "Carvanha",
  "pokemon_name_319": "Sharpedo",
  "pokemon_name_320": "Wailmer",
  "pokemon_name_321": "Wailord",
  "pokemon_name_322": "Chamallot",
  "pokemon_name_323": "Camérupt",
  "pokemon_name_324": "Chartor",
  "pokemon_name_325": "Spoink",
  "pokemon_name_326": "Groret",
  "pokemon_name_327": "Spinda",
  "pokemon_name_328": "Kraknoix",
  "pokemon_name_329": "Vibraninf",
  "pokemon_name_330": "Libégon",
  "pokemon_name_331": "Cacnea",
  "pokemon_name_332": "Cacturne",
  "pokemon_name_333": "Tylton",
  "pokemon_name_334": "Altaria",
  "pokemon_name_335": "Mangriff",
  "pokemon_name_336": "Séviper",
  "pokemon_name_337": "Séléroc",
  "pokemon_name_338": "Solaroc",
  "pokemon_name_339": "Barloche",
  "pokemon_name_340": "Barbicha",
  "pokemon_name_341": "Écrapince",
  "pokemon_name_342": "Colhomard",
  "pokemon_name_343": "Balbuto",
  "pokemon_name_344": "Kaorine",
  "pokemon_name_345": "Lilia",
  "pokemon_name_346": "Vacilys",
  "pokemon_name_347": "Anorith",
  "pokemon_name_348": "Armaldo",
  "pokemon_name_349": "Barpau",
  "pokemon_name_350": "Milobellus",
  "pokemon_name_351": "Morphéo",
  "pokemon_name_352": "Kecleon",
  "pokemon_name_353": "Polichombr",
  "pokemon_name_354": "Branette",
  "pokemon_name_355": "Skelénox",
  "pokemon_name_356": "Téraclope",
  "pokemon_name_357": "Tropius",
  "pokemon_name_358": "Éoko",
  "pokemon_name_359": "Absol",
  "pokemon_name_360": "Okéoké",
  "pokemon_name_361": "Stalgamin",
  "pokemon_name_362": "Oniglali",
  "pokemon_name_363": "Obalie",
  "pokemon_name_364": "Phogleur",
  "pokemon_name_365": "Kaimorse",
  "pokemon_name_366": "Coquiperl",
  "pokemon_name_367": "Serpang",
  "pokemon_name_368": "Rosabyss",
  "pokemon_name_369": "Relicanth",
  "pokemon_name_370": "Lovdisc",
  "pokemon_name_371": "Draby",
  "pokemon_name_372": "Drackhaus",
  "pokemon_name_373": "Drattak",
  "pokemon_name_374": "Terhal",
  "pokemon_name_375": "Métang",
  "pokemon_name_376": "Métalosse",
  "pokemon_name_377": "Regirock",
  "pokemon_name_378": "Regice",
  "pokemon_name_379": "Registeel",
  "pokemon_name_380": "Latias",
  "pokemon_name_381": "Latios",
  "pokemon_name_382": "Kyogre",
  "pokemon_name_383": "Groudon",
  "pokemon_name_384": "Rayquaza",
  "pokemon_name_385": "Jirachi",
  "pokemon_name_386": "Deoxys",
  "pokemon_name_387": "Tortipouss",
  "pokemon_name_388": "Boskara",
  "pokemon_name_389": "Torterra",
  "pokemon_name_390": "Ouisticram",
  "pokemon_name_391": "Chimpenfeu",
  "pokemon_name_392": "Simiabraz",
  "pokemon_name_393": "Tiplouf",
  "pokemon_name_394": "Prinplouf",
  "pokemon_name_395": "Pingoléon",
  "pokemon_name_396": "Étourmi",
  "pokemon_name_397": "Étourvol",
  "pokemon_name_398": "Étouraptor",
  "pokemon_name_399": "Keunotor",
  "pokemon_name_400": "Castorno",
  "pokemon_name_401": "Crikzik",
  "pokemon_name_402": "Mélokrik",
  "pokemon_name_403": "Lixy",
  "pokemon_name_404": "Luxio",
  "pokemon_name_405": "Luxray",
  "pokemon_name_406": "Rozbouton",
  "pokemon_name_407": "Roserade",
  "pokemon_name_408": "Kranidos",
  "pokemon_name_409": "Charkos",
  "pokemon_name_410": "Dinoclier",
  "pokemon_name_411": "Bastiodon",
  "pokemon_name_412": "Cheniti",
  "pokemon_name_413": "Cheniselle",
  "pokemon_name_414": "Papilord",
  "pokemon_name_415": "Apitrini",
  "pokemon_name_416": "Apireine",
  "pokemon_name_417": "Pachirisu",
  "pokemon_name_418": "Mustébouée",
  "pokemon_name_419": "Mustéflott",
  "pokemon_name_420": "Ceribou",
  "pokemon_name_421": "Ceriflor",
  "pokemon_name_422": "Sancoki",
  "pokemon_name_423": "Tritosor",
  "pokemon_name_424": "Capidextre",
  "pokemon_name_425": "Baudrive",
  "pokemon_name_426": "Grodrive",
  "pokemon_name_427": "Laporeille",
  "pokemon_name_428": "Lockpin",
  "pokemon_name_429": "Magirêve",
  "pokemon_name_430": "Corboss",
  "pokemon_name_431": "Chaglam",
  "pokemon_name_432": "Chaffreux",
  "pokemon_name_433": "Korillon",
  "pokemon_name_434": "Moufouette",
  "pokemon_name_435": "Moufflair",
  "pokemon_name_436": "Archéomire",
  "pokemon_name_437": "Archéodong",
  "pokemon_name_438": "Manzaï",
  "pokemon_name_439": "Mime Jr.",
  "pokemon_name_440": "Ptiravi",
  "pokemon_name_441": "Pijako",
  "pokemon_name_442": "Spiritomb",
  "pokemon_name_443": "Griknot",
  "pokemon_name_444": "Carmache",
  "pokemon_name_445": "Carchacrok",
  "pokemon_name_446": "Goinfrex",
  "pokemon_name_447": "Riolu",
  "pokemon_name_448": "Lucario",
  "pokemon_name_449": "Hippopotas",
  "pokemon_name_450": "Hippodocus",
  "pokemon_name_451": "Rapion",
  "pokemon_name_452": "Drascore",
  "pokemon_name_453": "Cradopaud",
  "pokemon_name_454": "Coatox",
  "pokemon_name_455": "Vortente",
  "pokemon_name_456": "Écayon",
  "pokemon_name_457": "Luminéon",
  "pokemon_name_458": "Babimanta",
  "pokemon_name_459": "Blizzi",
  "pokemon_name_460": "Blizzaroi",
  "pokemon_name_461": "Dimoret",
  "pokemon_name_462": "Magnézone",
  "pokemon_name_463": "Coudlangue",
  "pokemon_name_464": "Rhinastoc",
  "pokemon_name_465": "Bouldeneu",
  "pokemon_name_466": "Élekable",
  "pokemon_name_467": "Maganon",
  "pokemon_name_468": "Togekiss",
  "pokemon_name_469": "Yanmega",
  "pokemon_name_470": "Phyllali",
  "pokemon_name_471": "Givrali",
  "pokemon_name_472": "Scorvol",
  "pokemon_name_473": "Mammochon",
  "pokemon_name_474": "Porygon-Z",
  "pokemon_name_475": "Gallame",
  "pokemon_name_476": "Tarinorme",
  "pokemon_name_477": "Noctunoir",
  "pokemon_name_478": "Momartik",
  "pokemon_name_479": "Motisma",
  "pokemon_name_480": "Créhelf",
  "pokemon_name_481": "Créfollet",
  "pokemon_name_482": "Créfadet",
  "pokemon_name_483": "Dialga",
  "pokemon_name_484": "Palkia",
  "pokemon_name_485": "Heatran",
  "pokemon_name_486": "Regigigas",
  "pokemon_name_487": "Giratina",
  "pokemon_name_488": "Cresselia",
  "pokemon_name_489": "Phione",
  "pokemon_name_490": "Manaphy",
  "pokemon_name_491": "Darkrai",
  "pokemon_name_492": "Shaymin",
  "pokemon_name_493": "Arceus",
  "pokemon_name_494": "Victini",
  "pokemon_name_495": "Vipélierre",
  "pokemon_name_496": "Lianaja",
  "pokemon_name_497": "Majaspic",
  "pokemon_name_498": "Gruikui",
  "pokemon_name_499": "Grotichon",
  "pokemon_name_500": "Roitiflam",
  "pokemon_name_501": "Moustillon",
  "pokemon_name_502": "Mateloutre",
  "pokemon_name_503": "Clamiral",
  "pokemon_name_504": "Ratentif",
  "pokemon_name_505": "Miradar",
  "pokemon_name_506": "Ponchiot",
  "pokemon_name_507": "Ponchien",
  "pokemon_name_508": "Mastouffe",
  "pokemon_name_509": "Chacripan",
  "pokemon_name_510": "Léopardus",
  "pokemon_name_511": "Feuillajou",
  "pokemon_name_512": "Feuiloutan",
  "pokemon_name_513": "Flamajou",
  "pokemon_name_514": "Flamoutan",
  "pokemon_name_515": "Flotajou",
  "pokemon_name_516": "Flotoutan",
  "pokemon_name_517": "Munna",
  "pokemon_name_518": "Mushana",
  "pokemon_name_519": "Poichigeon",
  "pokemon_name_520": "Colombeau",
  "pokemon_name_521": "Déflaisan",
  "pokemon_name_522": "Zébibron",
  "pokemon_name_523": "Zéblitz",
  "pokemon_name_524": "Nodulithe",
  "pokemon_name_525": "Géolithe",
  "pokemon_name_526": "Gigalithe",
  "pokemon_name_527": "Chovsourir",
  "pokemon_name_528": "Rhinolove",
  "pokemon_name_529": "Rototaupe",
  "pokemon_name_530": "Minotaupe",
  "pokemon_name_531": "Nanméouïe",
  "pokemon_name_532": "Charpenti",
  "pokemon_name_533": "Ouvrifier",
  "pokemon_name_534": "Bétochef",
  "pokemon_name_535": "Tritonde",
  "pokemon_name_536": "Batracné",
  "pokemon_name_537": "Crapustule",
  "pokemon_name_538": "Judokrak",
  "pokemon_name_539": "Karaclée",
  "pokemon_name_540": "Larveyette",
  "pokemon_name_541": "Couverdure",
  "pokemon_name_542": "Manternel",
  "pokemon_name_543": "Venipatte",
  "pokemon_name_544": "Scobolide",
  "pokemon_name_545": "Brutapode",
  "pokemon_name_546": "Doudouvet",
  "pokemon_name_547": "Farfaduvet",
  "pokemon_name_548": "Chlorobule",
  "pokemon_name_549": "Fragilady",
  "pokemon_name_550": "Bargantua",
  "pokemon_name_551": "Mascaïman",
  "pokemon_name_552": "Escroco",
  "pokemon_name_553": "Crocorible",
  "pokemon_name_554": "Darumarond",
  "pokemon_name_555": "Darumacho",
  "pokemon_name_556": "Maracachi",
  "pokemon_name_557": "Crabicoque",
  "pokemon_name_558": "Crabaraque",
  "pokemon_name_559": "Baggiguane",
  "pokemon_name_560": "Baggaïd",
  "pokemon_name_561": "Cryptéro",
  "pokemon_name_562": "Tutafeh",
  "pokemon_name_563": "Tutankafer",
  "pokemon_name_564": "Carapagos",
  "pokemon_name_565": "Mégapagos",
  "pokemon_name_566": "Arkéapti",
  "pokemon_name_567": "Aéroptéryx",
  "pokemon_name_568": "Miamiasme",
  "pokemon_name_569": "Miasmax",
  "pokemon_name_570": "Zorua",
  "pokemon_name_571": "Zoroark",
  "pokemon_name_572": "Chinchidou",
  "pokemon_name_573": "Pashmilla",
  "pokemon_name_574": "Scrutella",
  "pokemon_name_575": "Mesmérella",
  "pokemon_name_576": "Sidérella",
  "pokemon_name_577": "Nucléos",
  "pokemon_name_578": "Méios",
  "pokemon_name_579": "Symbios",
  "pokemon_name_580": "Couaneton",
  "pokemon_name_581": "Lakmécygne",
  "pokemon_name_582": "Sorbébé",
  "pokemon_name_583": "Sorboul",
  "pokemon_name_584": "Sorbouboul",
  "pokemon_name_585": "Vivaldaim",
  "pokemon_name_586": "Haydaim",
  "pokemon_name_587": "Emolga",
  "pokemon_name_588": "Carabing",
  "pokemon_name_589": "Lançargot",
  "pokemon_name_590": "Trompignon",
  "pokemon_name_591": "Gaulet",
  "pokemon_name_592": "Viskuse",
  "pokemon_name_593": "Moyade",
  "pokemon_name_594": "Mamanbo",
  "pokemon_name_595": "Statitik",
  "pokemon_name_596": "Mygavolt",
  "pokemon_name_597": "Grindur",
  "pokemon_name_598": "Noacier",
  "pokemon_name_599": "Tic",
  "pokemon_name_600": "Clic",
  "pokemon_name_601": "Cliticlic",
  "pokemon_name_602": "Anchwatt",
  "pokemon_name_603": "Lampéroie",
  "pokemon_name_604": "Ohmassacre",
  "pokemon_name_605": "Lewsor",
  "pokemon_name_606": "Neitram",
  "pokemon_name_607": "Funécire",
  "pokemon_name_608": "Mélancolux",
  "pokemon_name_609": "Lugulabre",
  "pokemon_name_610": "Coupenotte",
  "pokemon_name_611": "Incisache",
  "pokemon_name_612": "Tranchodon",
  "pokemon_name_613": "Polarhume",
  "pokemon_name_614": "Polagriffe",
  "pokemon_name_615": "Hexagel",
  "pokemon_name_616": "Escargaume",
  "pokemon_name_617": "Limaspeed",
  "pokemon_name_618": "Limonde",
  "pokemon_name_619": "Kungfouine",
  "pokemon_name_620": "Shaofouine",
  "pokemon_name_621": "Drakkarmin",
  "pokemon_name_622": "Gringolem",
  "pokemon_name_623": "Golemastoc",
  "pokemon_name_624": "Scalpion",
  "pokemon_name_625": "Scalproie",
  "pokemon_name_626": "Frison",
  "pokemon_name_627": "Furaiglon",
  "pokemon_name_628": "Gueriaigle",
  "pokemon_name_629": "Vostourno",
  "pokemon_name_630": "Vaututrice",
  "pokemon_name_631": "Aflamanoir",
  "pokemon_name_632": "Fermite",
  "pokemon_name_633": "Solochi",
  "pokemon_name_634": "Diamat",
  "pokemon_name_635": "Trioxhydre",
  "pokemon_name_636": "Pyronille",
  "pokemon_name_637": "Pyrax",
  "pokemon_name_638": "Cobaltium",
  "pokemon_name_639": "Terrakium",
  "pokemon_name_640": "Viridium",
  "pokemon_name_641": "Boréas",
  "pokemon_name_642": "Fulguris",
  "pokemon_name_643": "Reshiram",
  "pokemon_name_644": "Zekrom",
  "pokemon_name_645": "Démétéros",
  "pokemon_name_646": "Kyurem",
  "pokemon_name_647": "Keldeo",
  "pokemon_name_648": "Meloetta",
  "pokemon_name_649": "Genesect",
  "pokemon_name_808": "Meltan",
  "pokemon_name_809": "Melmetal",
  "pokemon_name_862": "Ixon",
  "pokemon_name_863": "Berserkatt",
  "pokemon_name_865": "Palarticho"}